setup.py
subbehave/__init__.py
subbehave/context.py
subbehave/dispatcher.py
subbehave/formatter.py
subbehave/resource.py
subbehave.egg-info/PKG-INFO
subbehave.egg-info/SOURCES.txt
subbehave.egg-info/dependency_links.txt
subbehave.egg-info/requires.txt
subbehave.egg-info/top_level.txt
subbehave/command/__init__.py
subbehave/command/base.py
subbehave/command/describe_model.py
subbehave/unittest/__init__.py
subbehave/unittest/case.py
subbehave/unittest/consumer.py
subbehave/unittest/dispatcher.py
subbehave/unittest/result.py
subbehave/unittest/runner.py
subbehave/unittest/suite.py
subbehave/unittest/command/__init__.py
subbehave/unittest/command/result.py
subbehave/unittest/command/scope_transition.py