Metadata-Version: 1.1
Name: subbehave
Version: 0.0.1.0
Summary: Provide Behave step outcomes for consumption by another process.
Home-page: https://github.com/popham/subbehave
Author: Tim Popham
Author-email: popham@uw.edu
License: MIT
Download-URL: https://github.com/popham/subbehave/archive/0.0.1.0.tar.gz
Keywords: behave subbehave django gherkin
Platform: UNKNOWN
Classifier: Development Status :: 2 - Pre-Alpha
Classifier: Intended Audience :: Developers
Classifier: License :: OSI Approved :: MIT License
Classifier: Operating System :: OS Independent
Classifier: Topic :: Software Development
Classifier: Topic :: Software Development :: Testing
Classifier: Programming Language :: Python :: 3.3
Classifier: Programming Language :: Python :: 3.4
